sc_bilibili_file_utility/__init__.py
sc_bilibili_file_utility/main.py
sc_bilibili_file_utility/tests/__init__.py
sc_bilibili_file_utility/tests/sample_config/production.yml
sc_bilibili_file_utility-0.0.5.dist-info/LICENSE
sc_bilibili_file_utility-0.0.5.dist-info/METADATA
sc_bilibili_file_utility-0.0.5.dist-info/WHEEL
sc_bilibili_file_utility-0.0.5.dist-info/entry_points.txt
sc_bilibili_file_utility-0.0.5.dist-info/top_level.txt
sc_bilibili_file_utility-0.0.5.dist-info/RECORD
