Metadata-Version: 2.1
Name: sc-bilibili-file-utility
Version: 0.0.5
Summary: python project
Home-page: https://github.com/Scott-Lau/sc-bilibili-file-utility
Author: Scott Lau
Author-email: exceedego@126.com
License: MIT
Keywords: python
Platform: POSIX
Classifier: Programming Language :: Python :: 3
Classifier: Programming Language :: Python :: 3.6
Classifier: Programming Language :: Python :: 3.7
Classifier: Programming Language :: Python :: 3.8
Classifier: Programming Language :: Python :: 3.9
Classifier: Programming Language :: Python :: 3.10
Classifier: Programming Language :: Python :: 3.11
Classifier: License :: OSI Approved :: MIT License
Classifier: Operating System :: OS Independent
Classifier: Topic :: Software Development
Classifier: Topic :: Utilities
Requires-Python: >=3.6
License-File: LICENSE
Requires-Dist: sc-utilities >=0.0.11
Requires-Dist: sc-config >=0.0.11
